aikitx-1.0.0.dist-info/licenses/LICENSE
llmtoolkit/__init__.py
llmtoolkit/__main__.py
llmtoolkit/cli.py
llmtoolkit/original_main.py
llmtoolkit/platform_utils.py
llmtoolkit/resource_manager.py
llmtoolkit/app/__init__.py
llmtoolkit/app/main.py
llmtoolkit/app/backends/__init__.py
llmtoolkit/app/backends/ctransformers_backend.py
llmtoolkit/app/backends/llama_cpp_python_backend.py
llmtoolkit/app/backends/llamafile_backend.py
llmtoolkit/app/backends/transformers_backend.py
llmtoolkit/app/core/__init__.py
llmtoolkit/app/core/addon_manager.py
llmtoolkit/app/core/app_controller.py
llmtoolkit/app/core/backend_config_manager.py
llmtoolkit/app/core/backend_manager.py
llmtoolkit/app/core/backend_routing_system.py
llmtoolkit/app/core/background_processor.py
llmtoolkit/app/core/chat_config.py
llmtoolkit/app/core/chat_generator.py
llmtoolkit/app/core/chunked_summarization.py
llmtoolkit/app/core/config_manager.py
llmtoolkit/app/core/config_migration_tools.py
llmtoolkit/app/core/drag_drop_handler.py
llmtoolkit/app/core/enhanced_backend_manager.py
llmtoolkit/app/core/enhanced_error_reporting.py
llmtoolkit/app/core/enhanced_memory_manager.py
llmtoolkit/app/core/enhanced_model_validator.py
llmtoolkit/app/core/error_handling.py
llmtoolkit/app/core/error_handling_example.py
llmtoolkit/app/core/error_handling_test.py
llmtoolkit/app/core/error_integration.py
llmtoolkit/app/core/error_manager.py
llmtoolkit/app/core/error_messages.py
llmtoolkit/app/core/event_bus.py
llmtoolkit/app/core/gpu_acceleration.py
llmtoolkit/app/core/gpu_detector.py
llmtoolkit/app/core/hardware_detector.py
llmtoolkit/app/core/logging_config.py
llmtoolkit/app/core/memory_manager.py
llmtoolkit/app/core/model_backends.py
llmtoolkit/app/core/model_loader.py
llmtoolkit/app/core/model_loader_improved.py
llmtoolkit/app/core/model_manager.py
llmtoolkit/app/core/model_metadata_extractor.py
llmtoolkit/app/core/model_service.py
llmtoolkit/app/core/monitoring.py
llmtoolkit/app/core/performance_integration.py
llmtoolkit/app/core/performance_optimizer.py
aikitx-1.0.0.dist-info/METADATA
aikitx-1.0.0.dist-info/WHEEL
aikitx-1.0.0.dist-info/entry_points.txt
aikitx-1.0.0.dist-info/top_level.txt
aikitx-1.0.0.dist-info/RECORD
