Metadata-Version: 2.4
Name: aikitx
Version: 1.0.0
Summary: A comprehensive GUI toolkit for Large Language Models (LLMs) with GGUF support, document processing, email automation, and multi-backend inference
Author-email: Hussain Nazary <hussainnazary475@gmail.com>
License-Expression: MIT
Project-URL: Homepage, https://github.com/hussainnazary2/LLM-Toolkit
Project-URL: Repository, https://github.com/hussainnazary2/LLM-Toolkit
Project-URL: Documentation, https://github.com/hussainnazary2/LLM-Toolkit#readme
Project-URL: Bug Tracker, https://github.com/hussainnazary2/LLM-Toolkit/issues
Project-URL: Changelog, https://github.com/hussainnazary2/LLM-Toolkit/releases
Keywords: llm,ai,machine-learning,gguf,transformers,chatbot,nlp,gui,pyside6,llama-cpp,ctransformers,huggingface,document-processing,email-automation,pdf-processing,summarization,inference,neural-networks,deep-learning,language-models,text-generation,conversation-ai
Classifier: Development Status :: 4 - Beta
Classifier: Intended Audience :: Developers
Classifier: Intended Audience :: Science/Research
Classifier: Intended Audience :: End Users/Desktop
Classifier: Programming Language :: Python :: 3
Classifier: Programming Language :: Python :: 3.8
Classifier: Programming Language :: Python :: 3.9
Classifier: Programming Language :: Python :: 3.10
Classifier: Programming Language :: Python :: 3.11
Classifier: Programming Language :: Python :: 3.12
Classifier: Topic :: Scientific/Engineering :: Artificial Intelligence
Classifier: Topic :: Software Development :: Libraries :: Python Modules
Classifier: Topic :: Text Processing :: Linguistic
Classifier: Topic :: Communications :: Email
Classifier: Topic :: Office/Business :: Office Suites
Classifier: Topic :: Desktop Environment
Classifier: Operating System :: OS Independent
Classifier: Operating System :: Microsoft :: Windows
Classifier: Operating System :: MacOS
Classifier: Operating System :: POSIX :: Linux
Classifier: Environment :: X11 Applications :: Qt
Classifier: Environment :: Win32 (MS Windows)
Classifier: Environment :: MacOS X
Classifier: Natural Language :: English
Requires-Python: >=3.8
License-File: LICENSE
Requires-Dist: PySide6<7.0.0,>=6.4.0
Requires-Dist: llama-cpp-python<1.0.0,>=0.2.0
Requires-Dist: ctransformers<1.0.0,>=0.2.0
Requires-Dist: psutil<6.0.0,>=5.9.0
Requires-Dist: pynvml<12.0.0,>=11.4.1
Requires-Dist: pyyaml<7.0.0,>=6.0
Requires-Dist: jsonschema<5.0.0,>=4.17.3
Requires-Dist: appdirs<2.0.0,>=1.4.4
Requires-Dist: networkx<4.0.0,>=3.0
Requires-Dist: PyPDF2<4.0.0,>=3.0.0
Requires-Dist: pdfplumber<1.0.0,>=0.11.0
Requires-Dist: python-docx<2.0.0,>=0.8.11
Requires-Dist: requests<3.0.0,>=2.28.0
Requires-Dist: urllib3<3.0.0,>=1.26.0
Requires-Dist: importlib-resources<7.0.0,>=5.0.0; python_version < "3.9"
Requires-Dist: pywin32>=306; sys_platform == "win32"
Requires-Dist: pyobjc-framework-Cocoa>=9.0; sys_platform == "darwin"
Provides-Extra: transformers
Requires-Dist: transformers<5.0.0,>=4.30.0; extra == "transformers"
Requires-Dist: huggingface_hub<1.0.0,>=0.16.0; extra == "transformers"
Requires-Dist: safetensors<1.0.0,>=0.3.0; extra == "transformers"
Requires-Dist: accelerate<1.0.0,>=0.20.0; extra == "transformers"
Requires-Dist: tokenizers<1.0.0,>=0.13.0; extra == "transformers"
Provides-Extra: gpu
Requires-Dist: torch<3.0.0,>=2.0.0; extra == "gpu"
Requires-Dist: torchvision<1.0.0,>=0.15.0; extra == "gpu"
Provides-Extra: google
Requires-Dist: google-auth<3.0.0,>=2.17.0; extra == "google"
Requires-Dist: google-auth-oauthlib<2.0.0,>=1.0.0; extra == "google"
Requires-Dist: google-api-python-client<3.0.0,>=2.88.0; extra == "google"
Provides-Extra: dev
Requires-Dist: pytest<8.0.0,>=7.0.0; extra == "dev"
Requires-Dist: pytest-qt<5.0.0,>=4.0.0; extra == "dev"
Requires-Dist: pytest-cov<5.0.0,>=4.1.0; extra == "dev"
Requires-Dist: pytest-xvfb<4.0.0,>=3.0.0; extra == "dev"
Requires-Dist: pytest-timeout<3.0.0,>=2.1.0; extra == "dev"
Requires-Dist: pytest-mock<4.0.0,>=3.10.0; extra == "dev"
Requires-Dist: pytest-benchmark<5.0.0,>=4.0.0; extra == "dev"
Requires-Dist: pytest-html<4.0.0,>=3.1.0; extra == "dev"
Requires-Dist: pytest-json-report<2.0.0,>=1.5.0; extra == "dev"
Requires-Dist: pytest-parallel<1.0.0,>=0.1.1; extra == "dev"
Requires-Dist: black<25.0.0,>=23.1.0; extra == "dev"
Requires-Dist: isort<6.0.0,>=5.12.0; extra == "dev"
Requires-Dist: flake8<8.0.0,>=6.0.0; extra == "dev"
Requires-Dist: mypy<2.0.0,>=1.0.0; extra == "dev"
Requires-Dist: build<1.0.0,>=0.10.0; extra == "dev"
Requires-Dist: twine<5.0.0,>=4.0.0; extra == "dev"
Provides-Extra: all
Requires-Dist: transformers<5.0.0,>=4.30.0; extra == "all"
Requires-Dist: huggingface_hub<1.0.0,>=0.16.0; extra == "all"
Requires-Dist: safetensors<1.0.0,>=0.3.0; extra == "all"
Requires-Dist: accelerate<1.0.0,>=0.20.0; extra == "all"
Requires-Dist: tokenizers<1.0.0,>=0.13.0; extra == "all"
Requires-Dist: torch<3.0.0,>=2.0.0; extra == "all"
Requires-Dist: torchvision<1.0.0,>=0.15.0; extra == "all"
Requires-Dist: google-auth<3.0.0,>=2.17.0; extra == "all"
Requires-Dist: google-auth-oauthlib<2.0.0,>=1.0.0; extra == "all"
Requires-Dist: google-api-python-client<3.0.0,>=2.88.0; extra == "all"
Dynamic: license-file
